yafowil.plone-5.0.0-py3.11-nspkg.pth
yafowil/plone/__init__.py
yafowil/plone/config.py
yafowil/plone/configure.zcml
yafowil/plone/connectors.py
yafowil/plone/content.pt
yafowil/plone/form.py
yafowil/plone/interfaces.py
yafowil/plone/meta.py
yafowil/plone/meta.zcml
yafowil/plone/resources.py
yafowil/plone/setuphandlers.py
yafowil/plone/testing.py
yafowil/plone/autoform/__init__.py
yafowil/plone/autoform/behavior.py
yafowil/plone/autoform/configure.zcml
yafowil/plone/autoform/directives.py
yafowil/plone/autoform/events.py
yafowil/plone/autoform/factories.py
yafowil/plone/autoform/form.py
yafowil/plone/autoform/indexer.py
yafowil/plone/autoform/persistence.py
yafowil/plone/autoform/schema.py
yafowil/plone/examples/__init__.py
yafowil/plone/examples/configure.zcml
yafowil/plone/examples/view.pt
yafowil/plone/examples/view.py
yafowil/plone/profiles/autoform/catalog.xml
yafowil/plone/profiles/autoform/metadata.xml
yafowil/plone/profiles/autoform/registry.xml
yafowil/plone/profiles/default/browserlayer.xml
yafowil/plone/profiles/default/metadata.xml
yafowil/plone/profiles/default/registry.xml
yafowil/plone/profiles/demo/browserlayer.xml
yafowil/plone/profiles/demo/metadata.xml
yafowil/plone/profiles/demo/registry.xml
yafowil/plone/resources/widgets.js
yafowil/plone/resources/yafowil-fontello.css
yafowil/plone/resources/yafowil-fontello.eot
yafowil/plone/resources/yafowil-fontello.svg
yafowil/plone/resources/yafowil-fontello.ttf
yafowil/plone/resources/yafowil-fontello.woff
yafowil/plone/resources/yafowil-fontello.woff2
yafowil/plone/tests/__init__.py
yafowil/plone/tests/test_autoform_directives.py
yafowil/plone/tests/test_autoform_factories.py
yafowil/plone/tests/test_autoform_form.py
yafowil/plone/tests/test_autoform_immediate.py
yafowil/plone/tests/test_autoform_schema.py
yafowil/plone/tests/test_setup.py
yafowil/plone/widgets/__init__.py
yafowil/plone/widgets/datetime.py
yafowil/plone/widgets/label.py
yafowil/plone/widgets/recurrence.py
yafowil_plone-5.0.0.dist-info/licenses/LICENSE.rst
yafowil_plone-5.0.0.dist-info/METADATA
yafowil_plone-5.0.0.dist-info/WHEEL
yafowil_plone-5.0.0.dist-info/entry_points.txt
yafowil_plone-5.0.0.dist-info/namespace_packages.txt
yafowil_plone-5.0.0.dist-info/top_level.txt
yafowil_plone-5.0.0.dist-info/RECORD
