Metadata-Version: 2.4
Name: yafowil.plone
Version: 5.0.0
Summary: Plone Integration with YAFOWIL
Home-page: https://github.com/bluedynamics/yafowil.plone
Author: BlueDynamics Alliance
Author-email: dev@bluedynamics.com
License: BSD
Keywords: zope plone request response html input widgets form
Classifier: Environment :: Web Environment
Classifier: Framework :: Plone
Classifier: Framework :: Plone :: Addon
Classifier: Framework :: Plone :: 6.0
Classifier: Framework :: Plone :: 6.1
Classifier: Framework :: Plone :: 6.2
Classifier: Framework :: Zope
Classifier: Framework :: Zope :: 5
Classifier: License :: OSI Approved :: GNU General Public License (GPL)
Classifier: Operating System :: OS Independent
Classifier: Programming Language :: Python
Classifier: Programming Language :: Python :: 3.8
Classifier: Programming Language :: Python :: 3.9
Classifier: Programming Language :: Python :: 3.10
Classifier: Programming Language :: Python :: 3.11
Classifier: Programming Language :: Python :: 3.12
Classifier: Programming Language :: Python :: 3.13
Classifier: Topic :: Internet :: WWW/HTTP :: Dynamic Content
License-File: LICENSE.rst
Requires-Dist: setuptools>=39.1.0
Requires-Dist: node>=1.0
Requires-Dist: plone.api
Requires-Dist: plone.app.z3cform>=4.1.0
Requires-Dist: Products.CMFPlone>=6.0
Requires-Dist: yafowil.bootstrap>1.999
Requires-Dist: yafowil.yaml>=1.0.4
Requires-Dist: yafowil>2.3.2
Provides-Extra: test
Requires-Dist: plone.app.testing; extra == "test"
Requires-Dist: plone.app.robotframework; extra == "test"
Dynamic: license-file
